	<payment>
		<applicationId>100010</applicationId>
		<applicationName>test</applicationName>
		<channelId>100101</channelId>
		<operator>ALL</operator>
		<versionCode>100003</versionCode>
			<paytype>
				<id>100001</id>
				<name>中国移动游戏基地</name>
				<operators>01</operators>
				<province>00</province>
					<paygood>
						<feeCode>001</feeCode>
						<goodsName>Test</goodsName>
						<itemId>14010001</itemId>
						<money>2.0</money>
					</paygood>
					<paygood>
						<feeCode>002</feeCode>
						<goodsName>Test</goodsName>
						<itemId>14010002</itemId>
						<money>10.0</money>
					</paygood>
					<paygood>
						<feeCode>003</feeCode>
						<goodsName>Test</goodsName>
						<itemId>14010003</itemId>
						<money>20.0</money>
					</paygood>
			</paytype>
			<paytype>
				<id>100002</id>
				<name>中国联通游戏基地</name>
				<operators>02</operators>
				<province>00</province>
					<paygood>
						<feeCode>001</feeCode>
						<goodsName>Test</goodsName>
						<itemId>14010001</itemId>
						<money>2.0</money>
					</paygood>
					<paygood>
						<feeCode>002</feeCode>
						<goodsName>Test</goodsName>
						<itemId>14010002</itemId>
						<money>10.0</money>
					</paygood>
					<paygood>
						<feeCode>003</feeCode>
						<goodsName>Test</goodsName>
						<itemId>14010003</itemId>
						<money>20.0</money>
					</paygood>
			</paytype>
			<paytype>
				<id>100003</id>
				<name>中国电信游戏基地</name>
				<operators>03</operators>
				<province>00</province>
					<paygood>
						<feeCode>120625</feeCode>
						<goodsName>Test</goodsName>
						<itemId>14010001</itemId>
						<money>2.0</money>
					</paygood>
					<paygood>
						<feeCode>120627</feeCode>
						<goodsName>Test</goodsName>
						<itemId>14010002</itemId>
						<money>10.0</money>
					</paygood>
					<paygood>
						<feeCode>120628</feeCode>
						<goodsName>Test</goodsName>
						<itemId>14010003</itemId>
						<money>20.0</money>
					</paygood>
			</paytype>
	</payment>
	
